pydaymet/__init__.py
pydaymet/_utils.py
pydaymet/cli.py
pydaymet/core.py
pydaymet/exceptions.py
pydaymet/pet.py
pydaymet/print_versions.py
pydaymet/py.typed
pydaymet/pydaymet.py
pydaymet-0.19.4.dist-info/METADATA
pydaymet-0.19.4.dist-info/WHEEL
pydaymet-0.19.4.dist-info/entry_points.txt
pydaymet-0.19.4.dist-info/licenses/AUTHORS.rst
pydaymet-0.19.4.dist-info/licenses/LICENSE
pydaymet-0.19.4.dist-info/RECORD
